<?xml version="1.0" encoding="UTF-8"?>
<data>
	<post>
		<id>1800</id>
		<Title>IPT test</Title>
		<AuthorUsername>KAdmin</AuthorUsername>
		<Content></Content>
		<hidden_field_7622226433>interestingpeopletalks</hidden_field_7622226433>
		<youtube_url>https://www.youtube.com/watch?v=1OnBVqeW5JA</youtube_url>
		<main>videos</main>
		<category_1>health</category_1>
		<category-2></category-2>
		<category_3></category_3>
		<sub_1></sub_1>
		<sub_2></sub_2>
		<sub_1a></sub_1a>
		<sub_1b></sub_1b>
		<sub_1c></sub_1c>
		<sub_1d></sub_1d>
		<sub_1e></sub_1e>
		<sub_1f></sub_1f>
		<sub_1g></sub_1g>
		<sub_1h></sub_1h>
		<sub_1i></sub_1i>
		<ingredients></ingredients>
		<insecurity></insecurity>
		<business></business>
		<key_takeaway_1>kop 1 kop 1 kop 1</key_takeaway_1>
		<timestamp_1>01:30</timestamp_1>
		<text_1>blablablbalballablablablablabblablablab
nlblblblblba blablablabal </text_1>
		<key_takeaway_2>kop 1 kop 1 kop 1</key_takeaway_2>
		<timestamp_2>01:30</timestamp_2>
		<text_2>blablablbalballablablablablabblablablab
nlblblblblba blablablabal </text_2>
		<key_takeaway_3>kop 1 kop 1 kop 1</key_takeaway_3>
		<timestamp_3>01:30</timestamp_3>
		<text_3>blablablbalballablablablablabblablablab
nlblblblblba blablablabal </text_3>
		<add_extra_key_takeaway></add_extra_key_takeaway>
		<key_takeaway_4></key_takeaway_4>
		<timestamp_4></timestamp_4>
		<text_4></text_4>
		<key_takeaway_5></key_takeaway_5>
		<timestamp_5></timestamp_5>
		<text_5></text_5>
		<key_takeway_6></key_takeway_6>
		<timestamp_6></timestamp_6>
		<text_6></text_6>
		<key_takeway_7></key_takeway_7>
		<timestamp_7></timestamp_7>
		<text_7></text_7>
		<Tags></Tags>
		<_wpuf_form_id>1552</_wpuf_form_id>
		<wpuf_post_status></wpuf_post_status>
	</post>
	<post>
		<id>1802</id>
		<Title>IPT test</Title>
		<AuthorUsername>KAdmin</AuthorUsername>
		<Content></Content>
		<hidden_field_7622226433>interestingpeopletalks</hidden_field_7622226433>
		<youtube_url>https://www.youtube.com/watch?v=1OnBVqeW5JA</youtube_url>
		<main>shows</main>
		<category_1>happiness</category_1>
		<category-2></category-2>
		<category_3></category_3>
		<sub_1></sub_1>
		<sub_2></sub_2>
		<sub_1a></sub_1a>
		<sub_1b></sub_1b>
		<sub_1c></sub_1c>
		<sub_1d></sub_1d>
		<sub_1e></sub_1e>
		<sub_1f></sub_1f>
		<sub_1g></sub_1g>
		<sub_1h></sub_1h>
		<sub_1i></sub_1i>
		<ingredients></ingredients>
		<insecurity></insecurity>
		<business></business>
		<key_takeaway_1>kop 1 kop 1 kop 1</key_takeaway_1>
		<timestamp_1>01:30</timestamp_1>
		<text_1>blablablblablablabla blablablaba blablaba lbalbalab ablbalab laabla blablablaba blablaba lbalbalab ablbalab la</text_1>
		<key_takeaway_2>kop 1 kop 1 kop 1</key_takeaway_2>
		<timestamp_2>01:30</timestamp_2>
		<text_2>blablablblablablabla blablablaba blablaba lbalbalab ablbalab laabla blablablaba blablaba lbalbalab ablbalab la</text_2>
		<key_takeaway_3>kop 3 kop 3 kop 3</key_takeaway_3>
		<timestamp_3>01:30</timestamp_3>
		<text_3>blablablblablablabla blablablaba blablaba lbalbalab ablbalab laabla blablablaba blablaba lbalbalab ablbalab la</text_3>
		<add_extra_key_takeaway></add_extra_key_takeaway>
		<key_takeaway_4></key_takeaway_4>
		<timestamp_4></timestamp_4>
		<text_4></text_4>
		<key_takeaway_5></key_takeaway_5>
		<timestamp_5></timestamp_5>
		<text_5></text_5>
		<key_takeway_6></key_takeway_6>
		<timestamp_6></timestamp_6>
		<text_6></text_6>
		<key_takeway_7></key_takeway_7>
		<timestamp_7></timestamp_7>
		<text_7></text_7>
		<Tags></Tags>
		<_wpuf_form_id>1552</_wpuf_form_id>
		<wpuf_post_status></wpuf_post_status>
	</post>
	<post>
		<id>1804</id>
		<Title>IPT test</Title>
		<AuthorUsername>KAdmin</AuthorUsername>
		<Content></Content>
		<hidden_field_7622226433>interestingpeopletalks</hidden_field_7622226433>
		<youtube_url>https://soundcloud.com/liltecca/lil-tecca-ransom-1</youtube_url>
		<main>audio</main>
		<category_1>business</category_1>
		<category-2></category-2>
		<category_3></category_3>
		<sub_1></sub_1>
		<sub_2></sub_2>
		<sub_1a></sub_1a>
		<sub_1b></sub_1b>
		<sub_1c></sub_1c>
		<sub_1d></sub_1d>
		<sub_1e></sub_1e>
		<sub_1f></sub_1f>
		<sub_1g></sub_1g>
		<sub_1h></sub_1h>
		<sub_1i></sub_1i>
		<ingredients></ingredients>
		<insecurity></insecurity>
		<business></business>
		<key_takeaway_1>kop 1 kop 1 kop 1</key_takeaway_1>
		<timestamp_1>01:30</timestamp_1>
		<text_1>blbalbalbalbalbblbalbalbalbalbblbalbalbalbalbblbalbalbalbalbblbalbalbalbalb</text_1>
		<key_takeaway_2>kop 1 kop 1 kop 1</key_takeaway_2>
		<timestamp_2>01:30</timestamp_2>
		<text_2>blbalbalbalbalbblbalbalbalbalbblbalbalbalbalbblbalbalbalbalbblbalbalbalbalb</text_2>
		<key_takeaway_3>kop 1 kop 1 kop 1</key_takeaway_3>
		<timestamp_3>01:30</timestamp_3>
		<text_3>blbalbalbalbalbblbalbalbalbalbblbalbalbalbalbblbalbalbalbalbblbalbalbalbalb</text_3>
		<add_extra_key_takeaway></add_extra_key_takeaway>
		<key_takeaway_4></key_takeaway_4>
		<timestamp_4></timestamp_4>
		<text_4></text_4>
		<key_takeaway_5></key_takeaway_5>
		<timestamp_5></timestamp_5>
		<text_5></text_5>
		<key_takeway_6></key_takeway_6>
		<timestamp_6></timestamp_6>
		<text_6></text_6>
		<key_takeway_7></key_takeway_7>
		<timestamp_7></timestamp_7>
		<text_7></text_7>
		<Tags></Tags>
		<_wpuf_form_id>1552</_wpuf_form_id>
		<wpuf_post_status></wpuf_post_status>
	</post>
</data>